ilabs/brs/__init__.py
ilabs/brs/brs.py
ilabs/brs/evaluation.py
ilabs/brs/util.py
ilabs/brs/resources/BRS_XMLSchema_180417.xsd
ilabs.brs-1.0.1.dist-info/LICENSE
ilabs.brs-1.0.1.dist-info/METADATA
ilabs.brs-1.0.1.dist-info/WHEEL
ilabs.brs-1.0.1.dist-info/top_level.txt
ilabs.brs-1.0.1.dist-info/RECORD
